tess_py_api/__init__.py
tess_py_api/api.py
tess_py_api/dummy_class.py
tess_py_api/TessPyWrap/CpyAPI.py
tess_py_api/TessPyWrap/__init__.py
tess_py_api/TessPyWrap/capi_types.py
tess_py_api-0.0.12.dist-info/LICENSE
tess_py_api-0.0.12.dist-info/METADATA
tess_py_api-0.0.12.dist-info/WHEEL
tess_py_api-0.0.12.dist-info/top_level.txt
tess_py_api-0.0.12.dist-info/RECORD
