Metadata-Version: 2.1
Name: tess-py-api
Version: 0.0.12
Summary: UNKNOWN
Home-page: https://github.com/orel98/tess_py_api/tree/main
Author: Orel Kalaf
Author-email: orelron98@gmail.com
License: MIT
Platform: UNKNOWN
License-File: LICENSE
